api_stats.py
api_stats/__main__.py
api_stats/list.py
api_stats/plot.py
api_stats/utils.py
api_stats/record.py
api_stats/__init__.py
api_stats-0.3.dist-info/top_level.txt
api_stats-0.3.dist-info/entry_points.txt
api_stats-0.3.dist-info/METADATA
api_stats-0.3.dist-info/DESCRIPTION.rst
api_stats-0.3.dist-info/metadata.json
api_stats-0.3.dist-info/WHEEL
api_stats-0.3.dist-info/RECORD
