Metadata-Version: 2.0
Name: api-stats
Version: 0.3
Summary: Record historical statistics from an API that only offers current numbers.
Home-page: https://github.com/remram44/api_stats
Author: Remi Rampin
Author-email: remirampin@gmail.com
License: BSD
Keywords: api,log,record,stats,statistics,graph
Platform: UNKNOWN
Classifier: Development Status :: 3 - Alpha
Classifier: Intended Audience :: Developers
Classifier: Intended Audience :: System Administrators
Classifier: License :: OSI Approved :: BSD License
Classifier: Operating System :: OS Independent
Classifier: Topic :: Internet
Classifier: Topic :: Utilities
Requires-Dist: requests
